lolbuddy/__init__.py
lolbuddy-0.2.1.dist-info/DESCRIPTION.rst
lolbuddy-0.2.1.dist-info/METADATA
lolbuddy-0.2.1.dist-info/RECORD
lolbuddy-0.2.1.dist-info/WHEEL
lolbuddy-0.2.1.dist-info/entry_points.txt
lolbuddy-0.2.1.dist-info/metadata.json
lolbuddy-0.2.1.dist-info/top_level.txt
