Metadata-Version: 2.0
Name: lolbuddy
Version: 0.2.1
Summary: a cli tool to update league of legends itemsets and ability order from champion.gg
Home-page: https://github.com/CyrusRoshan/lolbuddy
Author: Cyrus Roshan
Author-email: hello@cyrusroshan.com
License: MIT
Keywords: lol,league,league of legends,item,ability
Platform: UNKNOWN
Requires-Dist: requests-futures (>=0.9.5)
